{
  "name": "John Smith",
  "socialName": "J. Smith",
  "email": "john.smith@example.com",
  "password": "securePassword123",
  "profile": {
    "name": "Employee"
  },
  "documents": [
    {
      "type": "CPF",
      "number": "123.456.789-00"
    },
    {
      "type": "RG",
      "number": "12.345.678-9"
    }
  ],
  "address": {
    "street": "Elm Street",
    "number": "42",
    "neighborhood": "Central",
    "city": "Springfield",
    "state": "IL",
    "zipCode": "62705"
  },
  "phone": {
    "areaCode": "21",
    "number": "99876-5432"
  }
}
